{"Races": {"VersionDateTime": "1900-01-01T00:00:00", "Race": [{"ID": "56460", "PrecinctsReporting": "29", "PrecinctsExpected": "29", "NumAbsenteeReporting": "1", "NumAbsenteeExpected": "1", "VoterCountQualified": "17002", "VoterCountVoted": "10200", "Choice": [{"ID": "107168", "VoteTotal": "1090", "Outcome": "Defeated"}, {"ID": "107773", "VoteTotal": "84", "Outcome": "Defeated"}, {"ID": "107391", "VoteTotal": "5563", "Outcome": "Runoff"}, {"ID": "108036", "VoteTotal": "59", "Outcome": "Defeated"}, {"ID": "107454", "VoteTotal": "64", "Outcome": "Defeated"}, {"ID": "106806", "VoteTotal": "3231", "Outcome": "Runoff"}]}, {"ID": "56461", "PrecinctsReporting": "29", "PrecinctsExpected": "29", "NumAbsenteeReporting": "1", "NumAbsenteeExpected": "1", "VoterCountQualified": "17002", "VoterCountVoted": "10200", "Choice": [{"ID": "108499", "VoteTotal": "3630", "Outcome": "Defeated"}, {"ID": "106316", "VoteTotal": "6207", "Outcome": "Elected"}]}, {"ID": "56462", "PrecinctsReporting": "29", "PrecinctsExpected": "29", "NumAbsenteeReporting": "1", "NumAbsenteeExpected": "1", "VoterCountQualified": "17002", "VoterCountVoted": "10200", "Choice": [{"ID": "106286", "VoteTotal": "4832", "Outcome": "Runoff"}, {"ID": "107499", "VoteTotal": "3651", "Outcome": "Runoff"}, {"ID": "108384", "VoteTotal": "956", "Outcome": "Defeated"}, {"ID": "108216", "VoteTotal": "351", "Outcome": "Defeated"}]}, {"ID": "56463", "PrecinctsReporting": "29", "PrecinctsExpected": "29", "NumAbsenteeReporting": "1", "NumAbsenteeExpected": "1", "VoterCountQualified": "17002", "VoterCountVoted": "10200", "Choice": [{"ID": "108495", "VoteTotal": "3801", "Outcome": "Defeated"}, {"ID": "106726", "VoteTotal": "6002", "Outcome": "Elected"}]}, {"ID": "56464", "PrecinctsReporting": "29", "PrecinctsExpected": "29", "NumAbsenteeReporting": "1", "NumAbsenteeExpected": "1", "VoterCountQualified": "17002", "VoterCountVoted": "10200", "Choice": [{"ID": "107267", "VoteTotal": "3900", "Outcome": "Defeated"}, {"ID": "108343", "VoteTotal": "416", "Outcome": "Defeated"}, {"ID": "107964", "VoteTotal": "5399", "Outcome": "Elected"}]}, {"ID": "56465", "PrecinctsReporting": "29", "PrecinctsExpected": "29", "NumAbsenteeReporting": "1", "NumAbsenteeExpected": "1", "VoterCountQualified": "17002", "VoterCountVoted": "10200", "Choice": [{"ID": "107682", "VoteTotal": "2245", "Outcome": "Defeated"}, {"ID": "108379", "VoteTotal": "798", "Outcome": "Defeated"}, {"ID": "106953", "VoteTotal": "5417", "Outcome": "Elected"}, {"ID": "107303", "VoteTotal": "688", "Outcome": "Defeated"}, {"ID": "108358", "VoteTotal": "547", "Outcome": "Defeated"}]}, {"ID": "56466", "PrecinctsReporting": "29", "PrecinctsExpected": "29", "NumAbsenteeReporting": "1", "NumAbsenteeExpected": "1", "VoterCountQualified": "17002", "VoterCountVoted": "10200", "Choice": [{"ID": "107470", "VoteTotal": "4190", "Outcome": "Elected"}, {"ID": "106293", "VoteTotal": "4817", "Outcome": "Defeated"}]}, {"ID": "56474", "PrecinctsReporting": "29", "PrecinctsExpected": "29", "NumAbsenteeReporting": "1", "NumAbsenteeExpected": "1", "VoterCountQualified": "17002", "VoterCountVoted": "10200", "Choice": [{"ID": "108243", "VoteTotal": "4619", "Outcome": "Elected"}, {"ID": "108055", "VoteTotal": "1206", "Outcome": "Defeated"}, {"ID": "108181", "VoteTotal": "1639", "Outcome": "Defeated"}, {"ID": "107277", "VoteTotal": "1214", "Outcome": "Defeated"}]}, {"ID": "56476", "PrecinctsReporting": "18", "PrecinctsExpected": "18", "NumAbsenteeReporting": "1", "NumAbsenteeExpected": "1", "VoterCountQualified": "10451", "VoterCountVoted": "6128", "Choice": [{"ID": "107133", "VoteTotal": "2188", "Outcome": "Defeated"}, {"ID": "106648", "VoteTotal": "3369", "Outcome": "Elected"}]}, {"ID": "56531", "PrecinctsReporting": "10", "PrecinctsExpected": "10", "NumAbsenteeReporting": "1", "NumAbsenteeExpected": "1", "VoterCountQualified": "8526", "VoterCountVoted": "5068", "Choice": [{"ID": "108476", "VoteTotal": "2270", "Outcome": "Defeated"}, {"ID": "106940", "VoteTotal": "2592", "Outcome": "Elected"}]}, {"ID": "57433", "PrecinctsReporting": "29", "PrecinctsExpected": "29", "NumAbsenteeReporting": "1", "NumAbsenteeExpected": "1", "VoterCountQualified": "17002", "VoterCountVoted": "10200", "Choice": [{"ID": "107621", "VoteTotal": "4353", "Outcome": "Runoff"}, {"ID": "108560", "VoteTotal": "1880", "Outcome": "Defeated"}, {"ID": "107502", "VoteTotal": "1270", "Outcome": "Defeated"}, {"ID": "107968", "VoteTotal": "2486", "Outcome": "Runoff"}]}, {"ID": "57432", "PrecinctsReporting": "29", "PrecinctsExpected": "29", "NumAbsenteeReporting": "1", "NumAbsenteeExpected": "1", "VoterCountQualified": "17002", "VoterCountVoted": "10200", "Choice": [{"ID": "106509", "VoteTotal": "6245", "Outcome": "Elected"}, {"ID": "107902", "VoteTotal": "3551", "Outcome": "Defeated"}]}, {"ID": "57424", "PrecinctsReporting": "3", "PrecinctsExpected": "3", "NumAbsenteeReporting": "1", "NumAbsenteeExpected": "1", "VoterCountQualified": "2682", "VoterCountVoted": "1665", "Choice": [{"ID": "107539", "VoteTotal": "629", "Outcome": "Defeated"}, {"ID": "107247", "VoteTotal": "964", "Outcome": "Elected"}]}, {"ID": "57425", "PrecinctsReporting": "4", "PrecinctsExpected": "4", "NumAbsenteeReporting": "1", "NumAbsenteeExpected": "1", "VoterCountQualified": "1557", "VoterCountVoted": "980", "Choice": [{"ID": "108273", "VoteTotal": "359", "Outcome": "Runoff"}, {"ID": "108272", "VoteTotal": "166", "Outcome": "Defeated"}, {"ID": "108245", "VoteTotal": "399", "Outcome": "Runoff"}]}, {"ID": "57426", "PrecinctsReporting": "5", "PrecinctsExpected": "5", "NumAbsenteeReporting": "1", "NumAbsenteeExpected": "1", "VoterCountQualified": "1783", "VoterCountVoted": "1272", "Choice": [{"ID": "107334", "VoteTotal": "423", "Outcome": "Defeated"}, {"ID": "107649", "VoteTotal": "834", "Outcome": "Elected"}]}, {"ID": "57427", "PrecinctsReporting": "5", "PrecinctsExpected": "5", "NumAbsenteeReporting": "1", "NumAbsenteeExpected": "1", "VoterCountQualified": "1956", "VoterCountVoted": "1112", "Choice": [{"ID": "107026", "VoteTotal": "436", "Outcome": "Defeated"}, {"ID": "106639", "VoteTotal": "599", "Outcome": "Elected"}]}, {"ID": "57429", "PrecinctsReporting": "3", "PrecinctsExpected": "3", "NumAbsenteeReporting": "1", "NumAbsenteeExpected": "1", "VoterCountQualified": "1875", "VoterCountVoted": "1165", "Choice": [{"ID": "108518", "VoteTotal": "402", "Outcome": "Runoff"}, {"ID": "106411", "VoteTotal": "352", "Outcome": "Runoff"}, {"ID": "106756", "VoteTotal": "137", "Outcome": "Defeated"}, {"ID": "108241", "VoteTotal": "244", "Outcome": "Defeated"}]}, {"ID": "57430", "PrecinctsReporting": "2", "PrecinctsExpected": "2", "NumAbsenteeReporting": "1", "NumAbsenteeExpected": "1", "VoterCountQualified": "1912", "VoterCountVoted": "1175", "Choice": [{"ID": "107729", "VoteTotal": "896", "Outcome": "Elected"}, {"ID": "106589", "VoteTotal": "243", "Outcome": "Defeated"}]}, {"ID": "57431", "PrecinctsReporting": "3", "PrecinctsExpected": "3", "NumAbsenteeReporting": "1", "NumAbsenteeExpected": "1", "VoterCountQualified": "1643", "VoterCountVoted": "800", "Choice": [{"ID": "107134", "VoteTotal": "131", "Outcome": "Defeated"}, {"ID": "108218", "VoteTotal": "230", "Outcome": "Defeated"}, {"ID": "106513", "VoteTotal": "394", "Outcome": "Elected"}]}, {"ID": "11521", "PrecinctsReporting": "29", "PrecinctsExpected": "29", "NumAbsenteeReporting": "1", "NumAbsenteeExpected": "1", "VoterCountQualified": "17002", "VoterCountVoted": "10200", "Choice": [{"ID": "3", "VoteTotal": "3739", "Outcome": null}, {"ID": "4", "VoteTotal": "5518", "Outcome": "Defeated"}]}, {"ID": "11522", "PrecinctsReporting": "29", "PrecinctsExpected": "29", "NumAbsenteeReporting": "1", "NumAbsenteeExpected": "1", "VoterCountQualified": "17002", "VoterCountVoted": "10200", "Choice": [{"ID": "3", "VoteTotal": "4213", "Outcome": "Approved"}, {"ID": "4", "VoteTotal": "5058", "Outcome": null}]}, {"ID": "11523", "PrecinctsReporting": "29", "PrecinctsExpected": "29", "NumAbsenteeReporting": "1", "NumAbsenteeExpected": "1", "VoterCountQualified": "17002", "VoterCountVoted": "10200", "Choice": [{"ID": "3", "VoteTotal": "4982", "Outcome": "Approved"}, {"ID": "4", "VoteTotal": "4248", "Outcome": null}]}, {"ID": "11524", "PrecinctsReporting": "29", "PrecinctsExpected": "29", "NumAbsenteeReporting": "1", "NumAbsenteeExpected": "1", "VoterCountQualified": "17002", "VoterCountVoted": "10200", "Choice": [{"ID": "3", "VoteTotal": "3117", "Outcome": null}, {"ID": "4", "VoteTotal": "6129", "Outcome": "Defeated"}]}]}}