{"Parishes": {"VersionDateTime": "1900-01-01T00:00:00", "Parish": [{"ParishValue": "01", "PrecinctsReporting": "59", "PrecinctsExpected": "59", "NumAbsenteeReporting": "1", "NumAbsenteeExpected": "1", "Choice": [{"ID": "62746", "VoteTotal": "11595", "Outcome": "Elected"}, {"ID": "62747", "VoteTotal": "3265", "Outcome": "Defeated"}]}, {"ParishValue": "10", "PrecinctsReporting": "118", "PrecinctsExpected": "118", "NumAbsenteeReporting": "1", "NumAbsenteeExpected": "1", "Choice": [{"ID": "62746", "VoteTotal": "30536", "Outcome": "Elected"}, {"ID": "62747", "VoteTotal": "13842", "Outcome": "Defeated"}]}, {"ParishValue": "12", "PrecinctsReporting": "13", "PrecinctsExpected": "13", "NumAbsenteeReporting": "1", "NumAbsenteeExpected": "1", "Choice": [{"ID": "62746", "VoteTotal": "1190", "Outcome": "Elected"}, {"ID": "62747", "VoteTotal": "281", "Outcome": "Defeated"}]}, {"ParishValue": "20", "PrecinctsReporting": "38", "PrecinctsExpected": "38", "NumAbsenteeReporting": "1", "NumAbsenteeExpected": "1", "Choice": [{"ID": "62746", "VoteTotal": "2787", "Outcome": "Elected"}, {"ID": "62747", "VoteTotal": "1822", "Outcome": "Defeated"}]}, {"ParishValue": "27", "PrecinctsReporting": "25", "PrecinctsExpected": "25", "NumAbsenteeReporting": "1", "NumAbsenteeExpected": "1", "Choice": [{"ID": "62746", "VoteTotal": "4455", "Outcome": "Elected"}, {"ID": "62747", "VoteTotal": "1768", "Outcome": "Defeated"}]}, {"ParishValue": "28", "PrecinctsReporting": "119", "PrecinctsExpected": "119", "NumAbsenteeReporting": "1", "NumAbsenteeExpected": "1", "Choice": [{"ID": "62746", "VoteTotal": "32430", "Outcome": "Elected"}, {"ID": "62747", "VoteTotal": "10920", "Outcome": "Defeated"}]}, {"ParishValue": "49", "PrecinctsReporting": "87", "PrecinctsExpected": "87", "NumAbsenteeReporting": "1", "NumAbsenteeExpected": "1", "Choice": [{"ID": "62746", "VoteTotal": "22325", "Outcome": "Elected"}, {"ID": "62747", "VoteTotal": "12673", "Outcome": "Defeated"}]}, {"ParishValue": "57", "PrecinctsReporting": "58", "PrecinctsExpected": "58", "NumAbsenteeReporting": "1", "NumAbsenteeExpected": "1", "Choice": [{"ID": "62746", "VoteTotal": "8402", "Outcome": "Elected"}, {"ID": "62747", "VoteTotal": "2562", "Outcome": "Defeated"}]}]}}