{"Parishes": {"VersionDateTime": "1900-01-01T00:00:00", "Parish": [{"ParishValue": "01", "PrecinctsReporting": "55", "PrecinctsExpected": "55", "NumAbsenteeReporting": "1", "NumAbsenteeExpected": "1", "VoterCountQualified": "19476", "VoterCountVoted": "4213", "Choice": [{"ID": "100157", "VoteTotal": "131", "Outcome": "Defeated"}, {"ID": "99011", "VoteTotal": "1863", "Outcome": "Elected"}, {"ID": "99808", "VoteTotal": "55", "Outcome": "Defeated"}, {"ID": "99156", "VoteTotal": "28", "Outcome": "Defeated"}, {"ID": "99760", "VoteTotal": "56", "Outcome": "Defeated"}, {"ID": "99339", "VoteTotal": "68", "Outcome": "Defeated"}, {"ID": "99317", "VoteTotal": "1087", "Outcome": "Defeated"}, {"ID": "100546", "VoteTotal": "26", "Outcome": "Defeated"}, {"ID": "99436", "VoteTotal": "40", "Outcome": "Defeated"}, {"ID": "99729", "VoteTotal": "112", "Outcome": "Defeated"}]}, {"ParishValue": "02", "PrecinctsReporting": "29", "PrecinctsExpected": "29", "NumAbsenteeReporting": "1", "NumAbsenteeExpected": "1", "VoterCountQualified": "7434", "VoterCountVoted": "1055", "Choice": [{"ID": "100157", "VoteTotal": "46", "Outcome": "Defeated"}, {"ID": "99011", "VoteTotal": "536", "Outcome": "Elected"}, {"ID": "99808", "VoteTotal": "5", "Outcome": "Defeated"}, {"ID": "99156", "VoteTotal": "4", "Outcome": "Defeated"}, {"ID": "99760", "VoteTotal": "12", "Outcome": "Defeated"}, {"ID": "99339", "VoteTotal": "16", "Outcome": "Defeated"}, {"ID": "99317", "VoteTotal": "297", "Outcome": "Defeated"}, {"ID": "100546", "VoteTotal": "5", "Outcome": "Defeated"}, {"ID": "99436", "VoteTotal": "6", "Outcome": "Defeated"}, {"ID": "99729", "VoteTotal": "45", "Outcome": "Defeated"}]}, {"ParishValue": "03", "PrecinctsReporting": "74", "PrecinctsExpected": "74", "NumAbsenteeReporting": "1", "NumAbsenteeExpected": "1", "VoterCountQualified": "28662", "VoterCountVoted": "6188", "Choice": [{"ID": "100157", "VoteTotal": "95", "Outcome": "Defeated"}, {"ID": "99011", "VoteTotal": "4222", "Outcome": "Elected"}, {"ID": "99808", "VoteTotal": "31", "Outcome": "Defeated"}, {"ID": "99156", "VoteTotal": "11", "Outcome": "Defeated"}, {"ID": "99760", "VoteTotal": "25", "Outcome": "Defeated"}, {"ID": "99339", "VoteTotal": "41", "Outcome": "Defeated"}, {"ID": "99317", "VoteTotal": "1384", "Outcome": "Defeated"}, {"ID": "100546", "VoteTotal": "31", "Outcome": "Defeated"}, {"ID": "99436", "VoteTotal": "24", "Outcome": "Defeated"}, {"ID": "99729", "VoteTotal": "74", "Outcome": "Defeated"}]}, {"ParishValue": "04", "PrecinctsReporting": "28", "PrecinctsExpected": "28", "NumAbsenteeReporting": "1", "NumAbsenteeExpected": "1", "VoterCountQualified": "9603", "VoterCountVoted": "1649", "Choice": [{"ID": "100157", "VoteTotal": "41", "Outcome": "Defeated"}, {"ID": "99011", "VoteTotal": "1139", "Outcome": "Elected"}, {"ID": "99808", "VoteTotal": "8", "Outcome": "Defeated"}, {"ID": "99156", "VoteTotal": "6", "Outcome": "Defeated"}, {"ID": "99760", "VoteTotal": "8", "Outcome": "Defeated"}, {"ID": "99339", "VoteTotal": "25", "Outcome": "Defeated"}, {"ID": "99317", "VoteTotal": "312", "Outcome": "Defeated"}, {"ID": "100546", "VoteTotal": "8", "Outcome": "Defeated"}, {"ID": "99436", "VoteTotal": "14", "Outcome": "Defeated"}, {"ID": "99729", "VoteTotal": "35", "Outcome": "Defeated"}]}, {"ParishValue": "05", "PrecinctsReporting": "49", "PrecinctsExpected": "49", "NumAbsenteeReporting": "1", "NumAbsenteeExpected": "1", "VoterCountQualified": "14350", "VoterCountVoted": "2030", "Choice": [{"ID": "100157", "VoteTotal": "71", "Outcome": "Defeated"}, {"ID": "99011", "VoteTotal": "1181", "Outcome": "Elected"}, {"ID": "99808", "VoteTotal": "16", "Outcome": "Defeated"}, {"ID": "99156", "VoteTotal": "12", "Outcome": "Defeated"}, {"ID": "99760", "VoteTotal": "8", "Outcome": "Defeated"}, {"ID": "99339", "VoteTotal": "27", "Outcome": "Defeated"}, {"ID": "99317", "VoteTotal": "455", "Outcome": "Defeated"}, {"ID": "100546", "VoteTotal": "12", "Outcome": "Defeated"}, {"ID": "99436", "VoteTotal": "9", "Outcome": "Defeated"}, {"ID": "99729", "VoteTotal": "54", "Outcome": "Defeated"}]}, {"ParishValue": "06", "PrecinctsReporting": "40", "PrecinctsExpected": "40", "NumAbsenteeReporting": "1", "NumAbsenteeExpected": "1", "VoterCountQualified": "7687", "VoterCountVoted": "1574", "Choice": [{"ID": "100157", "VoteTotal": "40", "Outcome": "Defeated"}, {"ID": "99011", "VoteTotal": "679", "Outcome": "Elected"}, {"ID": "99808", "VoteTotal": "20", "Outcome": "Defeated"}, {"ID": "99156", "VoteTotal": "6", "Outcome": "Defeated"}, {"ID": "99760", "VoteTotal": "11", "Outcome": "Defeated"}, {"ID": "99339", "VoteTotal": "31", "Outcome": "Defeated"}, {"ID": "99317", "VoteTotal": "391", "Outcome": "Defeated"}, {"ID": "100546", "VoteTotal": "8", "Outcome": "Defeated"}, {"ID": "99436", "VoteTotal": "22", "Outcome": "Defeated"}, {"ID": "99729", "VoteTotal": "61", "Outcome": "Defeated"}]}, {"ParishValue": "07", "PrecinctsReporting": "33", "PrecinctsExpected": "33", "NumAbsenteeReporting": "1", "NumAbsenteeExpected": "1", "VoterCountQualified": "5294", "VoterCountVoted": "1435", "Choice": [{"ID": "100157", "VoteTotal": "26", "Outcome": "Defeated"}, {"ID": "99011", "VoteTotal": "1056", "Outcome": "Elected"}, {"ID": "99808", "VoteTotal": "10", "Outcome": "Defeated"}, {"ID": "99156", "VoteTotal": "12", "Outcome": "Defeated"}, {"ID": "99760", "VoteTotal": "12", "Outcome": "Defeated"}, {"ID": "99339", "VoteTotal": "11", "Outcome": "Defeated"}, {"ID": "99317", "VoteTotal": "222", "Outcome": "Defeated"}, {"ID": "100546", "VoteTotal": "6", "Outcome": "Defeated"}, {"ID": "99436", "VoteTotal": "6", "Outcome": "Defeated"}, {"ID": "99729", "VoteTotal": "12", "Outcome": "Defeated"}]}, {"ParishValue": "08", "PrecinctsReporting": "81", "PrecinctsExpected": "81", "NumAbsenteeReporting": "1", "NumAbsenteeExpected": "1", "VoterCountQualified": "21074", "VoterCountVoted": "4595", "Choice": [{"ID": "100157", "VoteTotal": "66", "Outcome": "Defeated"}, {"ID": "99011", "VoteTotal": "2919", "Outcome": "Elected"}, {"ID": "99808", "VoteTotal": "24", "Outcome": "Defeated"}, {"ID": "99156", "VoteTotal": "19", "Outcome": "Defeated"}, {"ID": "99760", "VoteTotal": "24", "Outcome": "Defeated"}, {"ID": "99339", "VoteTotal": "47", "Outcome": "Defeated"}, {"ID": "99317", "VoteTotal": "1187", "Outcome": "Defeated"}, {"ID": "100546", "VoteTotal": "10", "Outcome": "Defeated"}, {"ID": "99436", "VoteTotal": "20", "Outcome": "Defeated"}, {"ID": "99729", "VoteTotal": "73", "Outcome": "Defeated"}]}, {"ParishValue": "09", "PrecinctsReporting": "151", "PrecinctsExpected": "151", "NumAbsenteeReporting": "1", "NumAbsenteeExpected": "1", "VoterCountQualified": "80683", "VoterCountVoted": "21457", "Choice": [{"ID": "100157", "VoteTotal": "215", "Outcome": "Defeated"}, {"ID": "99011", "VoteTotal": "16670", "Outcome": "Elected"}, {"ID": "99808", "VoteTotal": "67", "Outcome": "Defeated"}, {"ID": "99156", "VoteTotal": "44", "Outcome": "Defeated"}, {"ID": "99760", "VoteTotal": "45", "Outcome": "Defeated"}, {"ID": "99339", "VoteTotal": "111", "Outcome": "Defeated"}, {"ID": "99317", "VoteTotal": "3513", "Outcome": "Defeated"}, {"ID": "100546", "VoteTotal": "40", "Outcome": "Defeated"}, {"ID": "99436", "VoteTotal": "49", "Outcome": "Defeated"}, {"ID": "99729", "VoteTotal": "147", "Outcome": "Defeated"}]}, {"ParishValue": "10", "PrecinctsReporting": "123", "PrecinctsExpected": "123", "NumAbsenteeReporting": "1", "NumAbsenteeExpected": "1", "VoterCountQualified": "55958", "VoterCountVoted": "10562", "Choice": [{"ID": "100157", "VoteTotal": "193", "Outcome": "Defeated"}, {"ID": "99011", "VoteTotal": "6594", "Outcome": "Elected"}, {"ID": "99808", "VoteTotal": "63", "Outcome": "Defeated"}, {"ID": "99156", "VoteTotal": "24", "Outcome": "Defeated"}, {"ID": "99760", "VoteTotal": "59", "Outcome": "Defeated"}, {"ID": "99339", "VoteTotal": "99", "Outcome": "Defeated"}, {"ID": "99317", "VoteTotal": "2625", "Outcome": "Defeated"}, {"ID": "100546", "VoteTotal": "33", "Outcome": "Defeated"}, {"ID": "99436", "VoteTotal": "66", "Outcome": "Defeated"}, {"ID": "99729", "VoteTotal": "280", "Outcome": "Defeated"}]}, {"ParishValue": "11", "PrecinctsReporting": "19", "PrecinctsExpected": "19", "NumAbsenteeReporting": "1", "NumAbsenteeExpected": "1", "VoterCountQualified": "2851", "VoterCountVoted": "513", "Choice": [{"ID": "100157", "VoteTotal": "15", "Outcome": "Defeated"}, {"ID": "99011", "VoteTotal": "283", "Outcome": "Elected"}, {"ID": "99808", "VoteTotal": "3", "Outcome": "Defeated"}, {"ID": "99156", "VoteTotal": "10", "Outcome": "Defeated"}, {"ID": "99760", "VoteTotal": "11", "Outcome": "Defeated"}, {"ID": "99339", "VoteTotal": "8", "Outcome": "Defeated"}, {"ID": "99317", "VoteTotal": "127", "Outcome": "Defeated"}, {"ID": "100546", "VoteTotal": "1", "Outcome": "Defeated"}, {"ID": "99436", "VoteTotal": "5", "Outcome": "Defeated"}, {"ID": "99729", "VoteTotal": "26", "Outcome": "Defeated"}]}, {"ParishValue": "12", "PrecinctsReporting": "14", "PrecinctsExpected": "14", "NumAbsenteeReporting": "1", "NumAbsenteeExpected": "1", "VoterCountQualified": "2509", "VoterCountVoted": "386", "Choice": [{"ID": "100157", "VoteTotal": "14", "Outcome": "Defeated"}, {"ID": "99011", "VoteTotal": "123", "Outcome": "Elected"}, {"ID": "99808", "VoteTotal": "0", "Outcome": "Defeated"}, {"ID": "99156", "VoteTotal": "1", "Outcome": "Defeated"}, {"ID": "99760", "VoteTotal": "12", "Outcome": "Defeated"}, {"ID": "99339", "VoteTotal": "19", "Outcome": "Defeated"}, {"ID": "99317", "VoteTotal": "132", "Outcome": "Defeated"}, {"ID": "100546", "VoteTotal": "3", "Outcome": "Defeated"}, {"ID": "99436", "VoteTotal": "4", "Outcome": "Defeated"}, {"ID": "99729", "VoteTotal": "21", "Outcome": "Defeated"}]}, {"ParishValue": "13", "PrecinctsReporting": "26", "PrecinctsExpected": "26", "NumAbsenteeReporting": "1", "NumAbsenteeExpected": "1", "VoterCountQualified": "3802", "VoterCountVoted": "880", "Choice": [{"ID": "100157", "VoteTotal": "29", "Outcome": "Defeated"}, {"ID": "99011", "VoteTotal": "431", "Outcome": "Elected"}, {"ID": "99808", "VoteTotal": "5", "Outcome": "Defeated"}, {"ID": "99156", "VoteTotal": "1", "Outcome": "Defeated"}, {"ID": "99760", "VoteTotal": "6", "Outcome": "Defeated"}, {"ID": "99339", "VoteTotal": "9", "Outcome": "Defeated"}, {"ID": "99317", "VoteTotal": "194", "Outcome": "Defeated"}, {"ID": "100546", "VoteTotal": "5", "Outcome": "Defeated"}, {"ID": "99436", "VoteTotal": "7", "Outcome": "Defeated"}, {"ID": "99729", "VoteTotal": "24", "Outcome": "Defeated"}]}, {"ParishValue": "14", "PrecinctsReporting": "26", "PrecinctsExpected": "26", "NumAbsenteeReporting": "1", "NumAbsenteeExpected": "1", "VoterCountQualified": "4457", "VoterCountVoted": "1035", "Choice": [{"ID": "100157", "VoteTotal": "20", "Outcome": "Defeated"}, {"ID": "99011", "VoteTotal": "768", "Outcome": "Elected"}, {"ID": "99808", "VoteTotal": "6", "Outcome": "Defeated"}, {"ID": "99156", "VoteTotal": "2", "Outcome": "Defeated"}, {"ID": "99760", "VoteTotal": "14", "Outcome": "Defeated"}, {"ID": "99339", "VoteTotal": "8", "Outcome": "Defeated"}, {"ID": "99317", "VoteTotal": "158", "Outcome": "Defeated"}, {"ID": "100546", "VoteTotal": "3", "Outcome": "Defeated"}, {"ID": "99436", "VoteTotal": "2", "Outcome": "Defeated"}, {"ID": "99729", "VoteTotal": "25", "Outcome": "Defeated"}]}, {"ParishValue": "15", "PrecinctsReporting": "20", "PrecinctsExpected": "20", "NumAbsenteeReporting": "1", "NumAbsenteeExpected": "1", "VoterCountQualified": "6930", "VoterCountVoted": "2814", "Choice": [{"ID": "100157", "VoteTotal": "50", "Outcome": "Defeated"}, {"ID": "99011", "VoteTotal": "1830", "Outcome": "Elected"}, {"ID": "99808", "VoteTotal": "20", "Outcome": "Defeated"}, {"ID": "99156", "VoteTotal": "11", "Outcome": "Defeated"}, {"ID": "99760", "VoteTotal": "14", "Outcome": "Defeated"}, {"ID": "99339", "VoteTotal": "22", "Outcome": "Defeated"}, {"ID": "99317", "VoteTotal": "329", "Outcome": "Defeated"}, {"ID": "100546", "VoteTotal": "8", "Outcome": "Defeated"}, {"ID": "99436", "VoteTotal": "20", "Outcome": "Defeated"}, {"ID": "99729", "VoteTotal": "83", "Outcome": "Defeated"}]}, {"ParishValue": "16", "PrecinctsReporting": "37", "PrecinctsExpected": "37", "NumAbsenteeReporting": "1", "NumAbsenteeExpected": "1", "VoterCountQualified": "9118", "VoterCountVoted": "2018", "Choice": [{"ID": "100157", "VoteTotal": "35", "Outcome": "Defeated"}, {"ID": "99011", "VoteTotal": "1508", "Outcome": "Elected"}, {"ID": "99808", "VoteTotal": "7", "Outcome": "Defeated"}, {"ID": "99156", "VoteTotal": "11", "Outcome": "Defeated"}, {"ID": "99760", "VoteTotal": "13", "Outcome": "Defeated"}, {"ID": "99339", "VoteTotal": "13", "Outcome": "Defeated"}, {"ID": "99317", "VoteTotal": "318", "Outcome": "Defeated"}, {"ID": "100546", "VoteTotal": "4", "Outcome": "Defeated"}, {"ID": "99436", "VoteTotal": "10", "Outcome": "Defeated"}, {"ID": "99729", "VoteTotal": "36", "Outcome": "Defeated"}]}, {"ParishValue": "17", "PrecinctsReporting": "315", "PrecinctsExpected": "315", "NumAbsenteeReporting": "1", "NumAbsenteeExpected": "1", "VoterCountQualified": "137165", "VoterCountVoted": "43150", "Choice": [{"ID": "100157", "VoteTotal": "328", "Outcome": "Defeated"}, {"ID": "99011", "VoteTotal": "32977", "Outcome": "Elected"}, {"ID": "99808", "VoteTotal": "83", "Outcome": "Defeated"}, {"ID": "99156", "VoteTotal": "49", "Outcome": "Defeated"}, {"ID": "99760", "VoteTotal": "83", "Outcome": "Defeated"}, {"ID": "99339", "VoteTotal": "201", "Outcome": "Defeated"}, {"ID": "99317", "VoteTotal": "7976", "Outcome": "Defeated"}, {"ID": "100546", "VoteTotal": "81", "Outcome": "Defeated"}, {"ID": "99436", "VoteTotal": "80", "Outcome": "Defeated"}, {"ID": "99729", "VoteTotal": "217", "Outcome": "Defeated"}]}, {"ParishValue": "18", "PrecinctsReporting": "17", "PrecinctsExpected": "17", "NumAbsenteeReporting": "1", "NumAbsenteeExpected": "1", "VoterCountQualified": "3658", "VoterCountVoted": "587", "Choice": [{"ID": "100157", "VoteTotal": "5", "Outcome": "Defeated"}, {"ID": "99011", "VoteTotal": "508", "Outcome": "Elected"}, {"ID": "99808", "VoteTotal": "3", "Outcome": "Defeated"}, {"ID": "99156", "VoteTotal": "1", "Outcome": "Defeated"}, {"ID": "99760", "VoteTotal": "2", "Outcome": "Defeated"}, {"ID": "99339", "VoteTotal": "2", "Outcome": "Defeated"}, {"ID": "99317", "VoteTotal": "47", "Outcome": "Defeated"}, {"ID": "100546", "VoteTotal": "0", "Outcome": "Defeated"}, {"ID": "99436", "VoteTotal": "1", "Outcome": "Defeated"}, {"ID": "99729", "VoteTotal": "8", "Outcome": "Defeated"}]}, {"ParishValue": "19", "PrecinctsReporting": "24", "PrecinctsExpected": "24", "NumAbsenteeReporting": "1", "NumAbsenteeExpected": "1", "VoterCountQualified": "7250", "VoterCountVoted": "2553", "Choice": [{"ID": "100157", "VoteTotal": "45", "Outcome": "Defeated"}, {"ID": "99011", "VoteTotal": "1847", "Outcome": "Elected"}, {"ID": "99808", "VoteTotal": "15", "Outcome": "Defeated"}, {"ID": "99156", "VoteTotal": "9", "Outcome": "Defeated"}, {"ID": "99760", "VoteTotal": "13", "Outcome": "Defeated"}, {"ID": "99339", "VoteTotal": "27", "Outcome": "Defeated"}, {"ID": "99317", "VoteTotal": "347", "Outcome": "Defeated"}, {"ID": "100546", "VoteTotal": "8", "Outcome": "Defeated"}, {"ID": "99436", "VoteTotal": "9", "Outcome": "Defeated"}, {"ID": "99729", "VoteTotal": "61", "Outcome": "Defeated"}]}, {"ParishValue": "20", "PrecinctsReporting": "56", "PrecinctsExpected": "56", "NumAbsenteeReporting": "1", "NumAbsenteeExpected": "1", "VoterCountQualified": "12905", "VoterCountVoted": "2387", "Choice": [{"ID": "100157", "VoteTotal": "68", "Outcome": "Defeated"}, {"ID": "99011", "VoteTotal": "1319", "Outcome": "Elected"}, {"ID": "99808", "VoteTotal": "22", "Outcome": "Defeated"}, {"ID": "99156", "VoteTotal": "14", "Outcome": "Defeated"}, {"ID": "99760", "VoteTotal": "27", "Outcome": "Defeated"}, {"ID": "99339", "VoteTotal": "30", "Outcome": "Defeated"}, {"ID": "99317", "VoteTotal": "498", "Outcome": "Defeated"}, {"ID": "100546", "VoteTotal": "17", "Outcome": "Defeated"}, {"ID": "99436", "VoteTotal": "26", "Outcome": "Defeated"}, {"ID": "99729", "VoteTotal": "70", "Outcome": "Defeated"}]}, {"ParishValue": "21", "PrecinctsReporting": "26", "PrecinctsExpected": "26", "NumAbsenteeReporting": "1", "NumAbsenteeExpected": "1", "VoterCountQualified": "6744", "VoterCountVoted": "1054", "Choice": [{"ID": "100157", "VoteTotal": "26", "Outcome": "Defeated"}, {"ID": "99011", "VoteTotal": "650", "Outcome": "Elected"}, {"ID": "99808", "VoteTotal": "6", "Outcome": "Defeated"}, {"ID": "99156", "VoteTotal": "10", "Outcome": "Defeated"}, {"ID": "99760", "VoteTotal": "9", "Outcome": "Defeated"}, {"ID": "99339", "VoteTotal": "15", "Outcome": "Defeated"}, {"ID": "99317", "VoteTotal": "218", "Outcome": "Defeated"}, {"ID": "100546", "VoteTotal": "6", "Outcome": "Defeated"}, {"ID": "99436", "VoteTotal": "19", "Outcome": "Defeated"}, {"ID": "99729", "VoteTotal": "33", "Outcome": "Defeated"}]}, {"ParishValue": "22", "PrecinctsReporting": "34", "PrecinctsExpected": "34", "NumAbsenteeReporting": "1", "NumAbsenteeExpected": "1", "VoterCountQualified": "4748", "VoterCountVoted": "832", "Choice": [{"ID": "100157", "VoteTotal": "26", "Outcome": "Defeated"}, {"ID": "99011", "VoteTotal": "367", "Outcome": "Elected"}, {"ID": "99808", "VoteTotal": "10", "Outcome": "Defeated"}, {"ID": "99156", "VoteTotal": "3", "Outcome": "Defeated"}, {"ID": "99760", "VoteTotal": "7", "Outcome": "Defeated"}, {"ID": "99339", "VoteTotal": "20", "Outcome": "Defeated"}, {"ID": "99317", "VoteTotal": "247", "Outcome": "Defeated"}, {"ID": "100546", "VoteTotal": "8", "Outcome": "Defeated"}, {"ID": "99436", "VoteTotal": "10", "Outcome": "Defeated"}, {"ID": "99729", "VoteTotal": "57", "Outcome": "Defeated"}]}, {"ParishValue": "23", "PrecinctsReporting": "64", "PrecinctsExpected": "64", "NumAbsenteeReporting": "1", "NumAbsenteeExpected": "1", "VoterCountQualified": "22033", "VoterCountVoted": "3458", "Choice": [{"ID": "100157", "VoteTotal": "91", "Outcome": "Defeated"}, {"ID": "99011", "VoteTotal": "2171", "Outcome": "Elected"}, {"ID": "99808", "VoteTotal": "23", "Outcome": "Defeated"}, {"ID": "99156", "VoteTotal": "9", "Outcome": "Defeated"}, {"ID": "99760", "VoteTotal": "25", "Outcome": "Defeated"}, {"ID": "99339", "VoteTotal": "50", "Outcome": "Defeated"}, {"ID": "99317", "VoteTotal": "806", "Outcome": "Defeated"}, {"ID": "100546", "VoteTotal": "15", "Outcome": "Defeated"}, {"ID": "99436", "VoteTotal": "28", "Outcome": "Defeated"}, {"ID": "99729", "VoteTotal": "51", "Outcome": "Defeated"}]}, {"ParishValue": "24", "PrecinctsReporting": "44", "PrecinctsExpected": "44", "NumAbsenteeReporting": "1", "NumAbsenteeExpected": "1", "VoterCountQualified": "14338", "VoterCountVoted": "6003", "Choice": [{"ID": "100157", "VoteTotal": "151", "Outcome": "Defeated"}, {"ID": "99011", "VoteTotal": "3700", "Outcome": "Elected"}, {"ID": "99808", "VoteTotal": "32", "Outcome": "Defeated"}, {"ID": "99156", "VoteTotal": "24", "Outcome": "Defeated"}, {"ID": "99760", "VoteTotal": "44", "Outcome": "Defeated"}, {"ID": "99339", "VoteTotal": "101", "Outcome": "Defeated"}, {"ID": "99317", "VoteTotal": "1042", "Outcome": "Defeated"}, {"ID": "100546", "VoteTotal": "34", "Outcome": "Defeated"}, {"ID": "99436", "VoteTotal": "57", "Outcome": "Defeated"}, {"ID": "99729", "VoteTotal": "130", "Outcome": "Defeated"}]}, {"ParishValue": "25", "PrecinctsReporting": "31", "PrecinctsExpected": "31", "NumAbsenteeReporting": "1", "NumAbsenteeExpected": "1", "VoterCountQualified": "4691", "VoterCountVoted": "1463", "Choice": [{"ID": "100157", "VoteTotal": "39", "Outcome": "Defeated"}, {"ID": "99011", "VoteTotal": "827", "Outcome": "Elected"}, {"ID": "99808", "VoteTotal": "10", "Outcome": "Defeated"}, {"ID": "99156", "VoteTotal": "5", "Outcome": "Defeated"}, {"ID": "99760", "VoteTotal": "16", "Outcome": "Defeated"}, {"ID": "99339", "VoteTotal": "15", "Outcome": "Defeated"}, {"ID": "99317", "VoteTotal": "267", "Outcome": "Defeated"}, {"ID": "100546", "VoteTotal": "10", "Outcome": "Defeated"}, {"ID": "99436", "VoteTotal": "21", "Outcome": "Defeated"}, {"ID": "99729", "VoteTotal": "45", "Outcome": "Defeated"}]}, {"ParishValue": "26", "PrecinctsReporting": "271", "PrecinctsExpected": "271", "NumAbsenteeReporting": "1", "NumAbsenteeExpected": "1", "VoterCountQualified": "109516", "VoterCountVoted": "26911", "Choice": [{"ID": "100157", "VoteTotal": "428", "Outcome": "Defeated"}, {"ID": "99011", "VoteTotal": "17586", "Outcome": "Elected"}, {"ID": "99808", "VoteTotal": "97", "Outcome": "Defeated"}, {"ID": "99156", "VoteTotal": "42", "Outcome": "Defeated"}, {"ID": "99760", "VoteTotal": "89", "Outcome": "Defeated"}, {"ID": "99339", "VoteTotal": "187", "Outcome": "Defeated"}, {"ID": "99317", "VoteTotal": "7030", "Outcome": "Defeated"}, {"ID": "100546", "VoteTotal": "78", "Outcome": "Defeated"}, {"ID": "99436", "VoteTotal": "92", "Outcome": "Defeated"}, {"ID": "99729", "VoteTotal": "342", "Outcome": "Defeated"}]}, {"ParishValue": "27", "PrecinctsReporting": "22", "PrecinctsExpected": "22", "NumAbsenteeReporting": "1", "NumAbsenteeExpected": "1", "VoterCountQualified": "9692", "VoterCountVoted": "1396", "Choice": [{"ID": "100157", "VoteTotal": "38", "Outcome": "Defeated"}, {"ID": "99011", "VoteTotal": "738", "Outcome": "Elected"}, {"ID": "99808", "VoteTotal": "6", "Outcome": "Defeated"}, {"ID": "99156", "VoteTotal": "4", "Outcome": "Defeated"}, {"ID": "99760", "VoteTotal": "11", "Outcome": "Defeated"}, {"ID": "99339", "VoteTotal": "26", "Outcome": "Defeated"}, {"ID": "99317", "VoteTotal": "418", "Outcome": "Defeated"}, {"ID": "100546", "VoteTotal": "8", "Outcome": "Defeated"}, {"ID": "99436", "VoteTotal": "11", "Outcome": "Defeated"}, {"ID": "99729", "VoteTotal": "59", "Outcome": "Defeated"}]}, {"ParishValue": "28", "PrecinctsReporting": "128", "PrecinctsExpected": "128", "NumAbsenteeReporting": "1", "NumAbsenteeExpected": "1", "VoterCountQualified": "53839", "VoterCountVoted": "10457", "Choice": [{"ID": "100157", "VoteTotal": "119", "Outcome": "Defeated"}, {"ID": "99011", "VoteTotal": "5920", "Outcome": "Elected"}, {"ID": "99808", "VoteTotal": "33", "Outcome": "Defeated"}, {"ID": "99156", "VoteTotal": "22", "Outcome": "Defeated"}, {"ID": "99760", "VoteTotal": "31", "Outcome": "Defeated"}, {"ID": "99339", "VoteTotal": "81", "Outcome": "Defeated"}, {"ID": "99317", "VoteTotal": "3523", "Outcome": "Defeated"}, {"ID": "100546", "VoteTotal": "27", "Outcome": "Defeated"}, {"ID": "99436", "VoteTotal": "40", "Outcome": "Defeated"}, {"ID": "99729", "VoteTotal": "127", "Outcome": "Defeated"}]}, {"ParishValue": "29", "PrecinctsReporting": "73", "PrecinctsExpected": "73", "NumAbsenteeReporting": "1", "NumAbsenteeExpected": "1", "VoterCountQualified": "26696", "VoterCountVoted": "5708", "Choice": [{"ID": "100157", "VoteTotal": "181", "Outcome": "Defeated"}, {"ID": "99011", "VoteTotal": "2512", "Outcome": "Elected"}, {"ID": "99808", "VoteTotal": "53", "Outcome": "Defeated"}, {"ID": "99156", "VoteTotal": "31", "Outcome": "Defeated"}, {"ID": "99760", "VoteTotal": "54", "Outcome": "Defeated"}, {"ID": "99339", "VoteTotal": "80", "Outcome": "Defeated"}, {"ID": "99317", "VoteTotal": "1789", "Outcome": "Defeated"}, {"ID": "100546", "VoteTotal": "38", "Outcome": "Defeated"}, {"ID": "99436", "VoteTotal": "48", "Outcome": "Defeated"}, {"ID": "99729", "VoteTotal": "184", "Outcome": "Defeated"}]}, {"ParishValue": "30", "PrecinctsReporting": "24", "PrecinctsExpected": "24", "NumAbsenteeReporting": "1", "NumAbsenteeExpected": "1", "VoterCountQualified": "3552", "VoterCountVoted": "526", "Choice": [{"ID": "100157", "VoteTotal": "42", "Outcome": "Defeated"}, {"ID": "99011", "VoteTotal": "136", "Outcome": "Elected"}, {"ID": "99808", "VoteTotal": "6", "Outcome": "Defeated"}, {"ID": "99156", "VoteTotal": "3", "Outcome": "Defeated"}, {"ID": "99760", "VoteTotal": "8", "Outcome": "Defeated"}, {"ID": "99339", "VoteTotal": "10", "Outcome": "Defeated"}, {"ID": "99317", "VoteTotal": "184", "Outcome": "Defeated"}, {"ID": "100546", "VoteTotal": "7", "Outcome": "Defeated"}, {"ID": "99436", "VoteTotal": "22", "Outcome": "Defeated"}, {"ID": "99729", "VoteTotal": "33", "Outcome": "Defeated"}]}, {"ParishValue": "31", "PrecinctsReporting": "60", "PrecinctsExpected": "60", "NumAbsenteeReporting": "1", "NumAbsenteeExpected": "1", "VoterCountQualified": "11293", "VoterCountVoted": "2320", "Choice": [{"ID": "100157", "VoteTotal": "24", "Outcome": "Defeated"}, {"ID": "99011", "VoteTotal": "1692", "Outcome": "Elected"}, {"ID": "99808", "VoteTotal": "8", "Outcome": "Defeated"}, {"ID": "99156", "VoteTotal": "4", "Outcome": "Defeated"}, {"ID": "99760", "VoteTotal": "16", "Outcome": "Defeated"}, {"ID": "99339", "VoteTotal": "18", "Outcome": "Defeated"}, {"ID": "99317", "VoteTotal": "436", "Outcome": "Defeated"}, {"ID": "100546", "VoteTotal": "6", "Outcome": "Defeated"}, {"ID": "99436", "VoteTotal": "9", "Outcome": "Defeated"}, {"ID": "99729", "VoteTotal": "35", "Outcome": "Defeated"}]}, {"ParishValue": "32", "PrecinctsReporting": "78", "PrecinctsExpected": "78", "NumAbsenteeReporting": "1", "NumAbsenteeExpected": "1", "VoterCountQualified": "23511", "VoterCountVoted": "4001", "Choice": [{"ID": "100157", "VoteTotal": "140", "Outcome": "Defeated"}, {"ID": "99011", "VoteTotal": "1633", "Outcome": "Elected"}, {"ID": "99808", "VoteTotal": "46", "Outcome": "Defeated"}, {"ID": "99156", "VoteTotal": "23", "Outcome": "Defeated"}, {"ID": "99760", "VoteTotal": "36", "Outcome": "Defeated"}, {"ID": "99339", "VoteTotal": "76", "Outcome": "Defeated"}, {"ID": "99317", "VoteTotal": "1392", "Outcome": "Defeated"}, {"ID": "100546", "VoteTotal": "38", "Outcome": "Defeated"}, {"ID": "99436", "VoteTotal": "47", "Outcome": "Defeated"}, {"ID": "99729", "VoteTotal": "163", "Outcome": "Defeated"}]}, {"ParishValue": "33", "PrecinctsReporting": "26", "PrecinctsExpected": "26", "NumAbsenteeReporting": "1", "NumAbsenteeExpected": "1", "VoterCountQualified": "4591", "VoterCountVoted": "886", "Choice": [{"ID": "100157", "VoteTotal": "14", "Outcome": "Defeated"}, {"ID": "99011", "VoteTotal": "722", "Outcome": "Elected"}, {"ID": "99808", "VoteTotal": "9", "Outcome": "Defeated"}, {"ID": "99156", "VoteTotal": "5", "Outcome": "Defeated"}, {"ID": "99760", "VoteTotal": "2", "Outcome": "Defeated"}, {"ID": "99339", "VoteTotal": "11", "Outcome": "Defeated"}, {"ID": "99317", "VoteTotal": "98", "Outcome": "Defeated"}, {"ID": "100546", "VoteTotal": "3", "Outcome": "Defeated"}, {"ID": "99436", "VoteTotal": "3", "Outcome": "Defeated"}, {"ID": "99729", "VoteTotal": "10", "Outcome": "Defeated"}]}, {"ParishValue": "34", "PrecinctsReporting": "43", "PrecinctsExpected": "43", "NumAbsenteeReporting": "1", "NumAbsenteeExpected": "1", "VoterCountQualified": "9748", "VoterCountVoted": "2084", "Choice": [{"ID": "100157", "VoteTotal": "22", "Outcome": "Defeated"}, {"ID": "99011", "VoteTotal": "1513", "Outcome": "Elected"}, {"ID": "99808", "VoteTotal": "10", "Outcome": "Defeated"}, {"ID": "99156", "VoteTotal": "5", "Outcome": "Defeated"}, {"ID": "99760", "VoteTotal": "12", "Outcome": "Defeated"}, {"ID": "99339", "VoteTotal": "23", "Outcome": "Defeated"}, {"ID": "99317", "VoteTotal": "298", "Outcome": "Defeated"}, {"ID": "100546", "VoteTotal": "9", "Outcome": "Defeated"}, {"ID": "99436", "VoteTotal": "7", "Outcome": "Defeated"}, {"ID": "99729", "VoteTotal": "21", "Outcome": "Defeated"}]}, {"ParishValue": "35", "PrecinctsReporting": "50", "PrecinctsExpected": "50", "NumAbsenteeReporting": "1", "NumAbsenteeExpected": "1", "VoterCountQualified": "12372", "VoterCountVoted": "4181", "Choice": [{"ID": "100157", "VoteTotal": "79", "Outcome": "Defeated"}, {"ID": "99011", "VoteTotal": "2545", "Outcome": "Elected"}, {"ID": "99808", "VoteTotal": "36", "Outcome": "Defeated"}, {"ID": "99156", "VoteTotal": "13", "Outcome": "Defeated"}, {"ID": "99760", "VoteTotal": "27", "Outcome": "Defeated"}, {"ID": "99339", "VoteTotal": "68", "Outcome": "Defeated"}, {"ID": "99317", "VoteTotal": "846", "Outcome": "Defeated"}, {"ID": "100546", "VoteTotal": "15", "Outcome": "Defeated"}, {"ID": "99436", "VoteTotal": "20", "Outcome": "Defeated"}, {"ID": "99729", "VoteTotal": "87", "Outcome": "Defeated"}]}, {"ParishValue": "36", "PrecinctsReporting": "351", "PrecinctsExpected": "351", "NumAbsenteeReporting": "1", "NumAbsenteeExpected": "1", "VoterCountQualified": "157736", "VoterCountVoted": "54663", "Choice": [{"ID": "100157", "VoteTotal": "242", "Outcome": "Defeated"}, {"ID": "99011", "VoteTotal": "40650", "Outcome": "Elected"}, {"ID": "99808", "VoteTotal": "66", "Outcome": "Defeated"}, {"ID": "99156", "VoteTotal": "33", "Outcome": "Defeated"}, {"ID": "99760", "VoteTotal": "36", "Outcome": "Defeated"}, {"ID": "99339", "VoteTotal": "106", "Outcome": "Defeated"}, {"ID": "99317", "VoteTotal": "13101", "Outcome": "Defeated"}, {"ID": "100546", "VoteTotal": "49", "Outcome": "Defeated"}, {"ID": "99436", "VoteTotal": "43", "Outcome": "Defeated"}, {"ID": "99729", "VoteTotal": "85", "Outcome": "Defeated"}]}, {"ParishValue": "37", "PrecinctsReporting": "84", "PrecinctsExpected": "84", "NumAbsenteeReporting": "1", "NumAbsenteeExpected": "1", "VoterCountQualified": "41738", "VoterCountVoted": "12269", "Choice": [{"ID": "100157", "VoteTotal": "148", "Outcome": "Defeated"}, {"ID": "99011", "VoteTotal": "8996", "Outcome": "Elected"}, {"ID": "99808", "VoteTotal": "41", "Outcome": "Defeated"}, {"ID": "99156", "VoteTotal": "27", "Outcome": "Defeated"}, {"ID": "99760", "VoteTotal": "62", "Outcome": "Defeated"}, {"ID": "99339", "VoteTotal": "106", "Outcome": "Defeated"}, {"ID": "99317", "VoteTotal": "1803", "Outcome": "Defeated"}, {"ID": "100546", "VoteTotal": "47", "Outcome": "Defeated"}, {"ID": "99436", "VoteTotal": "70", "Outcome": "Defeated"}, {"ID": "99729", "VoteTotal": "140", "Outcome": "Defeated"}]}, {"ParishValue": "38", "PrecinctsReporting": "16", "PrecinctsExpected": "16", "NumAbsenteeReporting": "1", "NumAbsenteeExpected": "1", "VoterCountQualified": "6519", "VoterCountVoted": "981", "Choice": [{"ID": "100157", "VoteTotal": "13", "Outcome": "Defeated"}, {"ID": "99011", "VoteTotal": "674", "Outcome": "Elected"}, {"ID": "99808", "VoteTotal": "2", "Outcome": "Defeated"}, {"ID": "99156", "VoteTotal": "4", "Outcome": "Defeated"}, {"ID": "99760", "VoteTotal": "2", "Outcome": "Defeated"}, {"ID": "99339", "VoteTotal": "12", "Outcome": "Defeated"}, {"ID": "99317", "VoteTotal": "214", "Outcome": "Defeated"}, {"ID": "100546", "VoteTotal": "4", "Outcome": "Defeated"}, {"ID": "99436", "VoteTotal": "3", "Outcome": "Defeated"}, {"ID": "99729", "VoteTotal": "13", "Outcome": "Defeated"}]}, {"ParishValue": "39", "PrecinctsReporting": "28", "PrecinctsExpected": "28", "NumAbsenteeReporting": "1", "NumAbsenteeExpected": "1", "VoterCountQualified": "9454", "VoterCountVoted": "2245", "Choice": [{"ID": "100157", "VoteTotal": "44", "Outcome": "Defeated"}, {"ID": "99011", "VoteTotal": "1680", "Outcome": "Elected"}, {"ID": "99808", "VoteTotal": "16", "Outcome": "Defeated"}, {"ID": "99156", "VoteTotal": "8", "Outcome": "Defeated"}, {"ID": "99760", "VoteTotal": "17", "Outcome": "Defeated"}, {"ID": "99339", "VoteTotal": "18", "Outcome": "Defeated"}, {"ID": "99317", "VoteTotal": "352", "Outcome": "Defeated"}, {"ID": "100546", "VoteTotal": "7", "Outcome": "Defeated"}, {"ID": "99436", "VoteTotal": "14", "Outcome": "Defeated"}, {"ID": "99729", "VoteTotal": "35", "Outcome": "Defeated"}]}, {"ParishValue": "40", "PrecinctsReporting": "113", "PrecinctsExpected": "113", "NumAbsenteeReporting": "1", "NumAbsenteeExpected": "1", "VoterCountQualified": "37322", "VoterCountVoted": "7227", "Choice": [{"ID": "100157", "VoteTotal": "111", "Outcome": "Defeated"}, {"ID": "99011", "VoteTotal": "4722", "Outcome": "Elected"}, {"ID": "99808", "VoteTotal": "34", "Outcome": "Defeated"}, {"ID": "99156", "VoteTotal": "18", "Outcome": "Defeated"}, {"ID": "99760", "VoteTotal": "29", "Outcome": "Defeated"}, {"ID": "99339", "VoteTotal": "69", "Outcome": "Defeated"}, {"ID": "99317", "VoteTotal": "1451", "Outcome": "Defeated"}, {"ID": "100546", "VoteTotal": "28", "Outcome": "Defeated"}, {"ID": "99436", "VoteTotal": "41", "Outcome": "Defeated"}, {"ID": "99729", "VoteTotal": "119", "Outcome": "Defeated"}]}, {"ParishValue": "41", "PrecinctsReporting": "18", "PrecinctsExpected": "18", "NumAbsenteeReporting": "1", "NumAbsenteeExpected": "1", "VoterCountQualified": "3394", "VoterCountVoted": "730", "Choice": [{"ID": "100157", "VoteTotal": "16", "Outcome": "Defeated"}, {"ID": "99011", "VoteTotal": "530", "Outcome": "Elected"}, {"ID": "99808", "VoteTotal": "13", "Outcome": "Defeated"}, {"ID": "99156", "VoteTotal": "1", "Outcome": "Defeated"}, {"ID": "99760", "VoteTotal": "3", "Outcome": "Defeated"}, {"ID": "99339", "VoteTotal": "6", "Outcome": "Defeated"}, {"ID": "99317", "VoteTotal": "117", "Outcome": "Defeated"}, {"ID": "100546", "VoteTotal": "1", "Outcome": "Defeated"}, {"ID": "99436", "VoteTotal": "5", "Outcome": "Defeated"}, {"ID": "99729", "VoteTotal": "12", "Outcome": "Defeated"}]}, {"ParishValue": "42", "PrecinctsReporting": "25", "PrecinctsExpected": "25", "NumAbsenteeReporting": "1", "NumAbsenteeExpected": "1", "VoterCountQualified": "6451", "VoterCountVoted": "959", "Choice": [{"ID": "100157", "VoteTotal": "13", "Outcome": "Defeated"}, {"ID": "99011", "VoteTotal": "696", "Outcome": "Elected"}, {"ID": "99808", "VoteTotal": "4", "Outcome": "Defeated"}, {"ID": "99156", "VoteTotal": "3", "Outcome": "Defeated"}, {"ID": "99760", "VoteTotal": "13", "Outcome": "Defeated"}, {"ID": "99339", "VoteTotal": "9", "Outcome": "Defeated"}, {"ID": "99317", "VoteTotal": "135", "Outcome": "Defeated"}, {"ID": "100546", "VoteTotal": "4", "Outcome": "Defeated"}, {"ID": "99436", "VoteTotal": "9", "Outcome": "Defeated"}, {"ID": "99729", "VoteTotal": "28", "Outcome": "Defeated"}]}, {"ParishValue": "43", "PrecinctsReporting": "39", "PrecinctsExpected": "39", "NumAbsenteeReporting": "1", "NumAbsenteeExpected": "1", "VoterCountQualified": "6480", "VoterCountVoted": "849", "Choice": [{"ID": "100157", "VoteTotal": "38", "Outcome": "Defeated"}, {"ID": "99011", "VoteTotal": "388", "Outcome": "Elected"}, {"ID": "99808", "VoteTotal": "5", "Outcome": "Defeated"}, {"ID": "99156", "VoteTotal": "8", "Outcome": "Defeated"}, {"ID": "99760", "VoteTotal": "9", "Outcome": "Defeated"}, {"ID": "99339", "VoteTotal": "16", "Outcome": "Defeated"}, {"ID": "99317", "VoteTotal": "259", "Outcome": "Defeated"}, {"ID": "100546", "VoteTotal": "8", "Outcome": "Defeated"}, {"ID": "99436", "VoteTotal": "14", "Outcome": "Defeated"}, {"ID": "99729", "VoteTotal": "33", "Outcome": "Defeated"}]}, {"ParishValue": "44", "PrecinctsReporting": "31", "PrecinctsExpected": "31", "NumAbsenteeReporting": "1", "NumAbsenteeExpected": "1", "VoterCountQualified": "11701", "VoterCountVoted": "1783", "Choice": [{"ID": "100157", "VoteTotal": "35", "Outcome": "Defeated"}, {"ID": "99011", "VoteTotal": "1057", "Outcome": "Elected"}, {"ID": "99808", "VoteTotal": "7", "Outcome": "Defeated"}, {"ID": "99156", "VoteTotal": "5", "Outcome": "Defeated"}, {"ID": "99760", "VoteTotal": "12", "Outcome": "Defeated"}, {"ID": "99339", "VoteTotal": "11", "Outcome": "Defeated"}, {"ID": "99317", "VoteTotal": "527", "Outcome": "Defeated"}, {"ID": "100546", "VoteTotal": "7", "Outcome": "Defeated"}, {"ID": "99436", "VoteTotal": "8", "Outcome": "Defeated"}, {"ID": "99729", "VoteTotal": "27", "Outcome": "Defeated"}]}, {"ParishValue": "45", "PrecinctsReporting": "44", "PrecinctsExpected": "44", "NumAbsenteeReporting": "1", "NumAbsenteeExpected": "1", "VoterCountQualified": "14329", "VoterCountVoted": "3360", "Choice": [{"ID": "100157", "VoteTotal": "63", "Outcome": "Defeated"}, {"ID": "99011", "VoteTotal": "2245", "Outcome": "Elected"}, {"ID": "99808", "VoteTotal": "16", "Outcome": "Defeated"}, {"ID": "99156", "VoteTotal": "11", "Outcome": "Defeated"}, {"ID": "99760", "VoteTotal": "16", "Outcome": "Defeated"}, {"ID": "99339", "VoteTotal": "22", "Outcome": "Defeated"}, {"ID": "99317", "VoteTotal": "787", "Outcome": "Defeated"}, {"ID": "100546", "VoteTotal": "12", "Outcome": "Defeated"}, {"ID": "99436", "VoteTotal": "21", "Outcome": "Defeated"}, {"ID": "99729", "VoteTotal": "53", "Outcome": "Defeated"}]}, {"ParishValue": "46", "PrecinctsReporting": "11", "PrecinctsExpected": "11", "NumAbsenteeReporting": "1", "NumAbsenteeExpected": "1", "VoterCountQualified": "5688", "VoterCountVoted": "1766", "Choice": [{"ID": "100157", "VoteTotal": "12", "Outcome": "Defeated"}, {"ID": "99011", "VoteTotal": "1407", "Outcome": "Elected"}, {"ID": "99808", "VoteTotal": "5", "Outcome": "Defeated"}, {"ID": "99156", "VoteTotal": "7", "Outcome": "Defeated"}, {"ID": "99760", "VoteTotal": "12", "Outcome": "Defeated"}, {"ID": "99339", "VoteTotal": "16", "Outcome": "Defeated"}, {"ID": "99317", "VoteTotal": "186", "Outcome": "Defeated"}, {"ID": "100546", "VoteTotal": "5", "Outcome": "Defeated"}, {"ID": "99436", "VoteTotal": "12", "Outcome": "Defeated"}, {"ID": "99729", "VoteTotal": "18", "Outcome": "Defeated"}]}, {"ParishValue": "47", "PrecinctsReporting": "32", "PrecinctsExpected": "32", "NumAbsenteeReporting": "1", "NumAbsenteeExpected": "1", "VoterCountQualified": "11107", "VoterCountVoted": "2608", "Choice": [{"ID": "100157", "VoteTotal": "38", "Outcome": "Defeated"}, {"ID": "99011", "VoteTotal": "2114", "Outcome": "Elected"}, {"ID": "99808", "VoteTotal": "8", "Outcome": "Defeated"}, {"ID": "99156", "VoteTotal": "13", "Outcome": "Defeated"}, {"ID": "99760", "VoteTotal": "11", "Outcome": "Defeated"}, {"ID": "99339", "VoteTotal": "29", "Outcome": "Defeated"}, {"ID": "99317", "VoteTotal": "324", "Outcome": "Defeated"}, {"ID": "100546", "VoteTotal": "12", "Outcome": "Defeated"}, {"ID": "99436", "VoteTotal": "8", "Outcome": "Defeated"}, {"ID": "99729", "VoteTotal": "15", "Outcome": "Defeated"}]}, {"ParishValue": "48", "PrecinctsReporting": "39", "PrecinctsExpected": "39", "NumAbsenteeReporting": "1", "NumAbsenteeExpected": "1", "VoterCountQualified": "18230", "VoterCountVoted": "4580", "Choice": [{"ID": "100157", "VoteTotal": "41", "Outcome": "Defeated"}, {"ID": "99011", "VoteTotal": "3819", "Outcome": "Elected"}, {"ID": "99808", "VoteTotal": "15", "Outcome": "Defeated"}, {"ID": "99156", "VoteTotal": "7", "Outcome": "Defeated"}, {"ID": "99760", "VoteTotal": "6", "Outcome": "Defeated"}, {"ID": "99339", "VoteTotal": "13", "Outcome": "Defeated"}, {"ID": "99317", "VoteTotal": "564", "Outcome": "Defeated"}, {"ID": "100546", "VoteTotal": "4", "Outcome": "Defeated"}, {"ID": "99436", "VoteTotal": "11", "Outcome": "Defeated"}, {"ID": "99729", "VoteTotal": "21", "Outcome": "Defeated"}]}, {"ParishValue": "49", "PrecinctsReporting": "92", "PrecinctsExpected": "92", "NumAbsenteeReporting": "1", "NumAbsenteeExpected": "1", "VoterCountQualified": "34640", "VoterCountVoted": "6806", "Choice": [{"ID": "100157", "VoteTotal": "129", "Outcome": "Defeated"}, {"ID": "99011", "VoteTotal": "4606", "Outcome": "Elected"}, {"ID": "99808", "VoteTotal": "34", "Outcome": "Defeated"}, {"ID": "99156", "VoteTotal": "24", "Outcome": "Defeated"}, {"ID": "99760", "VoteTotal": "28", "Outcome": "Defeated"}, {"ID": "99339", "VoteTotal": "57", "Outcome": "Defeated"}, {"ID": "99317", "VoteTotal": "1184", "Outcome": "Defeated"}, {"ID": "100546", "VoteTotal": "23", "Outcome": "Defeated"}, {"ID": "99436", "VoteTotal": "34", "Outcome": "Defeated"}, {"ID": "99729", "VoteTotal": "93", "Outcome": "Defeated"}]}, {"ParishValue": "50", "PrecinctsReporting": "60", "PrecinctsExpected": "60", "NumAbsenteeReporting": "1", "NumAbsenteeExpected": "1", "VoterCountQualified": "18493", "VoterCountVoted": "3073", "Choice": [{"ID": "100157", "VoteTotal": "73", "Outcome": "Defeated"}, {"ID": "99011", "VoteTotal": "1869", "Outcome": "Elected"}, {"ID": "99808", "VoteTotal": "18", "Outcome": "Defeated"}, {"ID": "99156", "VoteTotal": "12", "Outcome": "Defeated"}, {"ID": "99760", "VoteTotal": "27", "Outcome": "Defeated"}, {"ID": "99339", "VoteTotal": "31", "Outcome": "Defeated"}, {"ID": "99317", "VoteTotal": "690", "Outcome": "Defeated"}, {"ID": "100546", "VoteTotal": "11", "Outcome": "Defeated"}, {"ID": "99436", "VoteTotal": "14", "Outcome": "Defeated"}, {"ID": "99729", "VoteTotal": "64", "Outcome": "Defeated"}]}, {"ParishValue": "51", "PrecinctsReporting": "51", "PrecinctsExpected": "51", "NumAbsenteeReporting": "1", "NumAbsenteeExpected": "1", "VoterCountQualified": "15588", "VoterCountVoted": "2836", "Choice": [{"ID": "100157", "VoteTotal": "64", "Outcome": "Defeated"}, {"ID": "99011", "VoteTotal": "1996", "Outcome": "Elected"}, {"ID": "99808", "VoteTotal": "13", "Outcome": "Defeated"}, {"ID": "99156", "VoteTotal": "11", "Outcome": "Defeated"}, {"ID": "99760", "VoteTotal": "12", "Outcome": "Defeated"}, {"ID": "99339", "VoteTotal": "23", "Outcome": "Defeated"}, {"ID": "99317", "VoteTotal": "535", "Outcome": "Defeated"}, {"ID": "100546", "VoteTotal": "6", "Outcome": "Defeated"}, {"ID": "99436", "VoteTotal": "17", "Outcome": "Defeated"}, {"ID": "99729", "VoteTotal": "60", "Outcome": "Defeated"}]}, {"ParishValue": "52", "PrecinctsReporting": "158", "PrecinctsExpected": "158", "NumAbsenteeReporting": "1", "NumAbsenteeExpected": "1", "VoterCountQualified": "41894", "VoterCountVoted": "11096", "Choice": [{"ID": "100157", "VoteTotal": "161", "Outcome": "Defeated"}, {"ID": "99011", "VoteTotal": "5996", "Outcome": "Elected"}, {"ID": "99808", "VoteTotal": "69", "Outcome": "Defeated"}, {"ID": "99156", "VoteTotal": "29", "Outcome": "Defeated"}, {"ID": "99760", "VoteTotal": "39", "Outcome": "Defeated"}, {"ID": "99339", "VoteTotal": "123", "Outcome": "Defeated"}, {"ID": "99317", "VoteTotal": "3800", "Outcome": "Defeated"}, {"ID": "100546", "VoteTotal": "31", "Outcome": "Defeated"}, {"ID": "99436", "VoteTotal": "56", "Outcome": "Defeated"}, {"ID": "99729", "VoteTotal": "171", "Outcome": "Defeated"}]}, {"ParishValue": "53", "PrecinctsReporting": "84", "PrecinctsExpected": "84", "NumAbsenteeReporting": "1", "NumAbsenteeExpected": "1", "VoterCountQualified": "32360", "VoterCountVoted": "6933", "Choice": [{"ID": "100157", "VoteTotal": "148", "Outcome": "Defeated"}, {"ID": "99011", "VoteTotal": "4268", "Outcome": "Elected"}, {"ID": "99808", "VoteTotal": "32", "Outcome": "Defeated"}, {"ID": "99156", "VoteTotal": "25", "Outcome": "Defeated"}, {"ID": "99760", "VoteTotal": "31", "Outcome": "Defeated"}, {"ID": "99339", "VoteTotal": "54", "Outcome": "Defeated"}, {"ID": "99317", "VoteTotal": "1656", "Outcome": "Defeated"}, {"ID": "100546", "VoteTotal": "24", "Outcome": "Defeated"}, {"ID": "99436", "VoteTotal": "39", "Outcome": "Defeated"}, {"ID": "99729", "VoteTotal": "221", "Outcome": "Defeated"}]}, {"ParishValue": "54", "PrecinctsReporting": "16", "PrecinctsExpected": "16", "NumAbsenteeReporting": "1", "NumAbsenteeExpected": "1", "VoterCountQualified": "2630", "VoterCountVoted": "609", "Choice": [{"ID": "100157", "VoteTotal": "18", "Outcome": "Defeated"}, {"ID": "99011", "VoteTotal": "492", "Outcome": "Elected"}, {"ID": "99808", "VoteTotal": "4", "Outcome": "Defeated"}, {"ID": "99156", "VoteTotal": "0", "Outcome": "Defeated"}, {"ID": "99760", "VoteTotal": "0", "Outcome": "Defeated"}, {"ID": "99339", "VoteTotal": "6", "Outcome": "Defeated"}, {"ID": "99317", "VoteTotal": "61", "Outcome": "Defeated"}, {"ID": "100546", "VoteTotal": "2", "Outcome": "Defeated"}, {"ID": "99436", "VoteTotal": "2", "Outcome": "Defeated"}, {"ID": "99729", "VoteTotal": "9", "Outcome": "Defeated"}]}, {"ParishValue": "55", "PrecinctsReporting": "95", "PrecinctsExpected": "95", "NumAbsenteeReporting": "1", "NumAbsenteeExpected": "1", "VoterCountQualified": "23543", "VoterCountVoted": "4173", "Choice": [{"ID": "100157", "VoteTotal": "101", "Outcome": "Defeated"}, {"ID": "99011", "VoteTotal": "2647", "Outcome": "Elected"}, {"ID": "99808", "VoteTotal": "16", "Outcome": "Defeated"}, {"ID": "99156", "VoteTotal": "21", "Outcome": "Defeated"}, {"ID": "99760", "VoteTotal": "24", "Outcome": "Defeated"}, {"ID": "99339", "VoteTotal": "41", "Outcome": "Defeated"}, {"ID": "99317", "VoteTotal": "1023", "Outcome": "Defeated"}, {"ID": "100546", "VoteTotal": "20", "Outcome": "Defeated"}, {"ID": "99436", "VoteTotal": "23", "Outcome": "Defeated"}, {"ID": "99729", "VoteTotal": "52", "Outcome": "Defeated"}]}, {"ParishValue": "56", "PrecinctsReporting": "30", "PrecinctsExpected": "30", "NumAbsenteeReporting": "1", "NumAbsenteeExpected": "1", "VoterCountQualified": "6746", "VoterCountVoted": "1214", "Choice": [{"ID": "100157", "VoteTotal": "30", "Outcome": "Defeated"}, {"ID": "99011", "VoteTotal": "822", "Outcome": "Elected"}, {"ID": "99808", "VoteTotal": "12", "Outcome": "Defeated"}, {"ID": "99156", "VoteTotal": "9", "Outcome": "Defeated"}, {"ID": "99760", "VoteTotal": "20", "Outcome": "Defeated"}, {"ID": "99339", "VoteTotal": "19", "Outcome": "Defeated"}, {"ID": "99317", "VoteTotal": "217", "Outcome": "Defeated"}, {"ID": "100546", "VoteTotal": "8", "Outcome": "Defeated"}, {"ID": "99436", "VoteTotal": "15", "Outcome": "Defeated"}, {"ID": "99729", "VoteTotal": "44", "Outcome": "Defeated"}]}, {"ParishValue": "57", "PrecinctsReporting": "56", "PrecinctsExpected": "56", "NumAbsenteeReporting": "1", "NumAbsenteeExpected": "1", "VoterCountQualified": "17920", "VoterCountVoted": "2089", "Choice": [{"ID": "100157", "VoteTotal": "50", "Outcome": "Defeated"}, {"ID": "99011", "VoteTotal": "1002", "Outcome": "Elected"}, {"ID": "99808", "VoteTotal": "10", "Outcome": "Defeated"}, {"ID": "99156", "VoteTotal": "7", "Outcome": "Defeated"}, {"ID": "99760", "VoteTotal": "18", "Outcome": "Defeated"}, {"ID": "99339", "VoteTotal": "35", "Outcome": "Defeated"}, {"ID": "99317", "VoteTotal": "648", "Outcome": "Defeated"}, {"ID": "100546", "VoteTotal": "9", "Outcome": "Defeated"}, {"ID": "99436", "VoteTotal": "22", "Outcome": "Defeated"}, {"ID": "99729", "VoteTotal": "55", "Outcome": "Defeated"}]}, {"ParishValue": "58", "PrecinctsReporting": "73", "PrecinctsExpected": "73", "NumAbsenteeReporting": "1", "NumAbsenteeExpected": "1", "VoterCountQualified": "9195", "VoterCountVoted": "1400", "Choice": [{"ID": "100157", "VoteTotal": "37", "Outcome": "Defeated"}, {"ID": "99011", "VoteTotal": "610", "Outcome": "Elected"}, {"ID": "99808", "VoteTotal": "10", "Outcome": "Defeated"}, {"ID": "99156", "VoteTotal": "5", "Outcome": "Defeated"}, {"ID": "99760", "VoteTotal": "13", "Outcome": "Defeated"}, {"ID": "99339", "VoteTotal": "27", "Outcome": "Defeated"}, {"ID": "99317", "VoteTotal": "442", "Outcome": "Defeated"}, {"ID": "100546", "VoteTotal": "7", "Outcome": "Defeated"}, {"ID": "99436", "VoteTotal": "17", "Outcome": "Defeated"}, {"ID": "99729", "VoteTotal": "66", "Outcome": "Defeated"}]}, {"ParishValue": "59", "PrecinctsReporting": "41", "PrecinctsExpected": "41", "NumAbsenteeReporting": "1", "NumAbsenteeExpected": "1", "VoterCountQualified": "14227", "VoterCountVoted": "2503", "Choice": [{"ID": "100157", "VoteTotal": "49", "Outcome": "Defeated"}, {"ID": "99011", "VoteTotal": "1664", "Outcome": "Elected"}, {"ID": "99808", "VoteTotal": "8", "Outcome": "Defeated"}, {"ID": "99156", "VoteTotal": "12", "Outcome": "Defeated"}, {"ID": "99760", "VoteTotal": "11", "Outcome": "Defeated"}, {"ID": "99339", "VoteTotal": "39", "Outcome": "Defeated"}, {"ID": "99317", "VoteTotal": "513", "Outcome": "Defeated"}, {"ID": "100546", "VoteTotal": "15", "Outcome": "Defeated"}, {"ID": "99436", "VoteTotal": "18", "Outcome": "Defeated"}, {"ID": "99729", "VoteTotal": "71", "Outcome": "Defeated"}]}, {"ParishValue": "60", "PrecinctsReporting": "40", "PrecinctsExpected": "40", "NumAbsenteeReporting": "1", "NumAbsenteeExpected": "1", "VoterCountQualified": "11539", "VoterCountVoted": "2613", "Choice": [{"ID": "100157", "VoteTotal": "54", "Outcome": "Defeated"}, {"ID": "99011", "VoteTotal": "1878", "Outcome": "Elected"}, {"ID": "99808", "VoteTotal": "11", "Outcome": "Defeated"}, {"ID": "99156", "VoteTotal": "13", "Outcome": "Defeated"}, {"ID": "99760", "VoteTotal": "14", "Outcome": "Defeated"}, {"ID": "99339", "VoteTotal": "22", "Outcome": "Defeated"}, {"ID": "99317", "VoteTotal": "436", "Outcome": "Defeated"}, {"ID": "100546", "VoteTotal": "11", "Outcome": "Defeated"}, {"ID": "99436", "VoteTotal": "19", "Outcome": "Defeated"}, {"ID": "99729", "VoteTotal": "52", "Outcome": "Defeated"}]}, {"ParishValue": "61", "PrecinctsReporting": "28", "PrecinctsExpected": "28", "NumAbsenteeReporting": "1", "NumAbsenteeExpected": "1", "VoterCountQualified": "8835", "VoterCountVoted": "3185", "Choice": [{"ID": "100157", "VoteTotal": "54", "Outcome": "Defeated"}, {"ID": "99011", "VoteTotal": "2179", "Outcome": "Elected"}, {"ID": "99808", "VoteTotal": "12", "Outcome": "Defeated"}, {"ID": "99156", "VoteTotal": "6", "Outcome": "Defeated"}, {"ID": "99760", "VoteTotal": "20", "Outcome": "Defeated"}, {"ID": "99339", "VoteTotal": "23", "Outcome": "Defeated"}, {"ID": "99317", "VoteTotal": "589", "Outcome": "Defeated"}, {"ID": "100546", "VoteTotal": "17", "Outcome": "Defeated"}, {"ID": "99436", "VoteTotal": "13", "Outcome": "Defeated"}, {"ID": "99729", "VoteTotal": "54", "Outcome": "Defeated"}]}, {"ParishValue": "62", "PrecinctsReporting": "17", "PrecinctsExpected": "17", "NumAbsenteeReporting": "1", "NumAbsenteeExpected": "1", "VoterCountQualified": "2895", "VoterCountVoted": "361", "Choice": [{"ID": "100157", "VoteTotal": "18", "Outcome": "Defeated"}, {"ID": "99011", "VoteTotal": "171", "Outcome": "Elected"}, {"ID": "99808", "VoteTotal": "1", "Outcome": "Defeated"}, {"ID": "99156", "VoteTotal": "2", "Outcome": "Defeated"}, {"ID": "99760", "VoteTotal": "8", "Outcome": "Defeated"}, {"ID": "99339", "VoteTotal": "3", "Outcome": "Defeated"}, {"ID": "99317", "VoteTotal": "110", "Outcome": "Defeated"}, {"ID": "100546", "VoteTotal": "2", "Outcome": "Defeated"}, {"ID": "99436", "VoteTotal": "14", "Outcome": "Defeated"}, {"ID": "99729", "VoteTotal": "20", "Outcome": "Defeated"}]}, {"ParishValue": "63", "PrecinctsReporting": "36", "PrecinctsExpected": "36", "NumAbsenteeReporting": "1", "NumAbsenteeExpected": "1", "VoterCountQualified": "3528", "VoterCountVoted": "1153", "Choice": [{"ID": "100157", "VoteTotal": "16", "Outcome": "Defeated"}, {"ID": "99011", "VoteTotal": "902", "Outcome": "Elected"}, {"ID": "99808", "VoteTotal": "4", "Outcome": "Defeated"}, {"ID": "99156", "VoteTotal": "4", "Outcome": "Defeated"}, {"ID": "99760", "VoteTotal": "6", "Outcome": "Defeated"}, {"ID": "99339", "VoteTotal": "9", "Outcome": "Defeated"}, {"ID": "99317", "VoteTotal": "166", "Outcome": "Defeated"}, {"ID": "100546", "VoteTotal": "1", "Outcome": "Defeated"}, {"ID": "99436", "VoteTotal": "2", "Outcome": "Defeated"}, {"ID": "99729", "VoteTotal": "16", "Outcome": "Defeated"}]}, {"ParishValue": "64", "PrecinctsReporting": "35", "PrecinctsExpected": "35", "NumAbsenteeReporting": "1", "NumAbsenteeExpected": "1", "VoterCountQualified": "4397", "VoterCountVoted": "871", "Choice": [{"ID": "100157", "VoteTotal": "16", "Outcome": "Defeated"}, {"ID": "99011", "VoteTotal": "488", "Outcome": "Elected"}, {"ID": "99808", "VoteTotal": "7", "Outcome": "Defeated"}, {"ID": "99156", "VoteTotal": "3", "Outcome": "Defeated"}, {"ID": "99760", "VoteTotal": "16", "Outcome": "Defeated"}, {"ID": "99339", "VoteTotal": "9", "Outcome": "Defeated"}, {"ID": "99317", "VoteTotal": "193", "Outcome": "Defeated"}, {"ID": "100546", "VoteTotal": "7", "Outcome": "Defeated"}, {"ID": "99436", "VoteTotal": "5", "Outcome": "Defeated"}, {"ID": "99729", "VoteTotal": "24", "Outcome": "Defeated"}]}]}}