{"Races": {"VersionDateTime": "1900-01-01T00:00:00", "Race": [{"ID": "47638", "PrecinctsReporting": "24", "PrecinctsExpected": "24", "NumAbsenteeReporting": "1", "NumAbsenteeExpected": "1", "VoterCountQualified": "8615", "VoterCountVoted": "5143", "Choice": [{"ID": "95035", "VoteTotal": "91", "Outcome": "Defeated"}, {"ID": "91638", "VoteTotal": "2885", "Outcome": "Runoff"}, {"ID": "93365", "VoteTotal": "137", "Outcome": "Defeated"}, {"ID": "92863", "VoteTotal": "722", "Outcome": "Runoff"}, {"ID": "95341", "VoteTotal": "972", "Outcome": "Defeated"}, {"ID": "92379", "VoteTotal": "57", "Outcome": "Defeated"}, {"ID": "95997", "VoteTotal": "12", "Outcome": "Defeated"}, {"ID": "93993", "VoteTotal": "16", "Outcome": "Defeated"}]}, {"ID": "47643", "PrecinctsReporting": "24", "PrecinctsExpected": "24", "NumAbsenteeReporting": "1", "NumAbsenteeExpected": "1", "VoterCountQualified": "8615", "VoterCountVoted": "5143", "Choice": [{"ID": "91683", "VoteTotal": "1827", "Outcome": "Runoff"}, {"ID": "95439", "VoteTotal": "25", "Outcome": "Defeated"}, {"ID": "91618", "VoteTotal": "158", "Outcome": "Defeated"}, {"ID": "94575", "VoteTotal": "1329", "Outcome": "Defeated"}, {"ID": "96016", "VoteTotal": "309", "Outcome": "Defeated"}, {"ID": "92920", "VoteTotal": "366", "Outcome": "Runoff"}, {"ID": "95111", "VoteTotal": "704", "Outcome": "Defeated"}, {"ID": "95924", "VoteTotal": "22", "Outcome": "Defeated"}, {"ID": "91626", "VoteTotal": "220", "Outcome": "Defeated"}]}, {"ID": "48751", "PrecinctsReporting": "2", "PrecinctsExpected": "2", "NumAbsenteeReporting": "1", "NumAbsenteeExpected": "1", "VoterCountQualified": "893", "VoterCountVoted": "562", "Choice": [{"ID": "95182", "VoteTotal": "355", "Outcome": "Elected"}, {"ID": "94794", "VoteTotal": "160", "Outcome": "Defeated"}]}, {"ID": "48752", "PrecinctsReporting": "2", "PrecinctsExpected": "2", "NumAbsenteeReporting": "1", "NumAbsenteeExpected": "1", "VoterCountQualified": "969", "VoterCountVoted": "559", "Choice": [{"ID": "94802", "VoteTotal": "162", "Outcome": "Defeated"}, {"ID": "93335", "VoteTotal": "367", "Outcome": "Elected"}]}, {"ID": "48753", "PrecinctsReporting": "5", "PrecinctsExpected": "5", "NumAbsenteeReporting": "1", "NumAbsenteeExpected": "1", "VoterCountQualified": "895", "VoterCountVoted": "567", "Choice": [{"ID": "93289", "VoteTotal": "193", "Outcome": "Defeated"}, {"ID": "95582", "VoteTotal": "351", "Outcome": "Elected"}]}, {"ID": "48740", "PrecinctsReporting": "4", "PrecinctsExpected": "4", "NumAbsenteeReporting": "1", "NumAbsenteeExpected": "1", "VoterCountQualified": "2600", "VoterCountVoted": "1662", "Choice": [{"ID": "95955", "VoteTotal": "543", "Outcome": "Defeated"}, {"ID": "92683", "VoteTotal": "876", "Outcome": "Elected"}]}, {"ID": "48734", "PrecinctsReporting": "7", "PrecinctsExpected": "7", "NumAbsenteeReporting": "1", "NumAbsenteeExpected": "1", "VoterCountQualified": "1864", "VoterCountVoted": "1126", "Choice": [{"ID": "95804", "VoteTotal": "687", "Outcome": "Elected"}, {"ID": "95894", "VoteTotal": "320", "Outcome": "Defeated"}]}, {"ID": "48742", "PrecinctsReporting": "4", "PrecinctsExpected": "4", "NumAbsenteeReporting": "1", "NumAbsenteeExpected": "1", "VoterCountQualified": "1908", "VoterCountVoted": "1404", "Choice": [{"ID": "95980", "VoteTotal": "254", "Outcome": "Defeated"}, {"ID": "92823", "VoteTotal": "635", "Outcome": "Runoff"}, {"ID": "93936", "VoteTotal": "495", "Outcome": "Runoff"}]}, {"ID": "48729", "PrecinctsReporting": "4", "PrecinctsExpected": "4", "NumAbsenteeReporting": "1", "NumAbsenteeExpected": "1", "VoterCountQualified": "1908", "VoterCountVoted": "1404", "Choice": [{"ID": "92413", "VoteTotal": "772", "Outcome": "Elected"}, {"ID": "94335", "VoteTotal": "602", "Outcome": "Defeated"}]}, {"ID": "48731", "PrecinctsReporting": "1", "PrecinctsExpected": "1", "NumAbsenteeReporting": "1", "NumAbsenteeExpected": "1", "VoterCountQualified": "221", "VoterCountVoted": "127", "Choice": [{"ID": "93818", "VoteTotal": "22", "Outcome": "Defeated"}, {"ID": "94671", "VoteTotal": "41", "Outcome": "Runoff"}, {"ID": "95686", "VoteTotal": "58", "Outcome": "Runoff"}]}, {"ID": "48727", "PrecinctsReporting": "1", "PrecinctsExpected": "1", "NumAbsenteeReporting": "1", "NumAbsenteeExpected": "1", "VoterCountQualified": "221", "VoterCountVoted": "127", "Choice": [{"ID": "95770", "VoteTotal": "71", "Outcome": "Elected"}, {"ID": "95841", "VoteTotal": "40", "Outcome": "Defeated"}, {"ID": "93180", "VoteTotal": "74", "Outcome": "Elected"}, {"ID": "95781", "VoteTotal": "82", "Outcome": "Elected"}, {"ID": "94657", "VoteTotal": "89", "Outcome": "Elected"}, {"ID": "95435", "VoteTotal": "75", "Outcome": "Elected"}]}, {"ID": "48728", "PrecinctsReporting": "1", "PrecinctsExpected": "1", "NumAbsenteeReporting": "1", "NumAbsenteeExpected": "1", "VoterCountQualified": "428", "VoterCountVoted": "217", "Choice": [{"ID": "95387", "VoteTotal": "129", "Outcome": "Elected"}, {"ID": "94781", "VoteTotal": "130", "Outcome": "Elected"}, {"ID": "96001", "VoteTotal": "115", "Outcome": "Defeated"}, {"ID": "92781", "VoteTotal": "153", "Outcome": "Elected"}, {"ID": "92987", "VoteTotal": "151", "Outcome": "Elected"}, {"ID": "94980", "VoteTotal": "123", "Outcome": "Elected"}]}, {"ID": "48736", "PrecinctsReporting": "4", "PrecinctsExpected": "4", "NumAbsenteeReporting": "1", "NumAbsenteeExpected": "1", "VoterCountQualified": "1908", "VoterCountVoted": "1404", "Choice": [{"ID": "95541", "VoteTotal": "489", "Outcome": "Defeated"}, {"ID": "95130", "VoteTotal": "805", "Outcome": "Elected"}, {"ID": "92624", "VoteTotal": "871", "Outcome": "Elected"}, {"ID": "94888", "VoteTotal": "698", "Outcome": "Elected"}, {"ID": "92578", "VoteTotal": "935", "Outcome": "Elected"}, {"ID": "92309", "VoteTotal": "1045", "Outcome": "Elected"}, {"ID": "95288", "VoteTotal": "621", "Outcome": "Defeated"}, {"ID": "95115", "VoteTotal": "380", "Outcome": "Defeated"}]}, {"ID": "9696", "PrecinctsReporting": "24", "PrecinctsExpected": "24", "NumAbsenteeReporting": "1", "NumAbsenteeExpected": "1", "VoterCountQualified": "8615", "VoterCountVoted": "5143", "Choice": [{"ID": "3", "VoteTotal": "3591", "Outcome": "Approved"}, {"ID": "4", "VoteTotal": "1268", "Outcome": null}]}, {"ID": "9697", "PrecinctsReporting": "24", "PrecinctsExpected": "24", "NumAbsenteeReporting": "1", "NumAbsenteeExpected": "1", "VoterCountQualified": "8615", "VoterCountVoted": "5143", "Choice": [{"ID": "3", "VoteTotal": "3597", "Outcome": "Approved"}, {"ID": "4", "VoteTotal": "1252", "Outcome": null}]}, {"ID": "9705", "PrecinctsReporting": "24", "PrecinctsExpected": "24", "NumAbsenteeReporting": "1", "NumAbsenteeExpected": "1", "VoterCountQualified": "8615", "VoterCountVoted": "5143", "Choice": [{"ID": "3", "VoteTotal": "2338", "Outcome": null}, {"ID": "4", "VoteTotal": "2417", "Outcome": "Defeated"}]}, {"ID": "9699", "PrecinctsReporting": "24", "PrecinctsExpected": "24", "NumAbsenteeReporting": "1", "NumAbsenteeExpected": "1", "VoterCountQualified": "8615", "VoterCountVoted": "5143", "Choice": [{"ID": "3", "VoteTotal": "799", "Outcome": null}, {"ID": "4", "VoteTotal": "3925", "Outcome": "Defeated"}]}, {"ID": "9700", "PrecinctsReporting": "24", "PrecinctsExpected": "24", "NumAbsenteeReporting": "1", "NumAbsenteeExpected": "1", "VoterCountQualified": "8615", "VoterCountVoted": "5143", "Choice": [{"ID": "3", "VoteTotal": "2535", "Outcome": null}, {"ID": "4", "VoteTotal": "2226", "Outcome": "Defeated"}]}, {"ID": "9701", "PrecinctsReporting": "24", "PrecinctsExpected": "24", "NumAbsenteeReporting": "1", "NumAbsenteeExpected": "1", "VoterCountQualified": "8615", "VoterCountVoted": "5143", "Choice": [{"ID": "3", "VoteTotal": "2677", "Outcome": "Approved"}, {"ID": "4", "VoteTotal": "1994", "Outcome": null}]}, {"ID": "9702", "PrecinctsReporting": "24", "PrecinctsExpected": "24", "NumAbsenteeReporting": "1", "NumAbsenteeExpected": "1", "VoterCountQualified": "8615", "VoterCountVoted": "5143", "Choice": [{"ID": "3", "VoteTotal": "3888", "Outcome": "Approved"}, {"ID": "4", "VoteTotal": "837", "Outcome": null}]}, {"ID": "9703", "PrecinctsReporting": "24", "PrecinctsExpected": "24", "NumAbsenteeReporting": "1", "NumAbsenteeExpected": "1", "VoterCountQualified": "8615", "VoterCountVoted": "5143", "Choice": [{"ID": "3", "VoteTotal": "3091", "Outcome": "Approved"}, {"ID": "4", "VoteTotal": "1628", "Outcome": null}]}, {"ID": "9704", "PrecinctsReporting": "24", "PrecinctsExpected": "24", "NumAbsenteeReporting": "1", "NumAbsenteeExpected": "1", "VoterCountQualified": "8615", "VoterCountVoted": "5143", "Choice": [{"ID": "3", "VoteTotal": "3087", "Outcome": null}, {"ID": "4", "VoteTotal": "1599", "Outcome": "Defeated"}]}, {"ID": "9698", "PrecinctsReporting": "24", "PrecinctsExpected": "24", "NumAbsenteeReporting": "1", "NumAbsenteeExpected": "1", "VoterCountQualified": "8615", "VoterCountVoted": "5143", "Choice": [{"ID": "3", "VoteTotal": "2779", "Outcome": "Approved"}, {"ID": "4", "VoteTotal": "1908", "Outcome": null}]}, {"ID": "9706", "PrecinctsReporting": "24", "PrecinctsExpected": "24", "NumAbsenteeReporting": "1", "NumAbsenteeExpected": "1", "VoterCountQualified": "8615", "VoterCountVoted": "5143", "Choice": [{"ID": "3", "VoteTotal": "799", "Outcome": null}, {"ID": "4", "VoteTotal": "3910", "Outcome": "Defeated"}]}, {"ID": "9707", "PrecinctsReporting": "24", "PrecinctsExpected": "24", "NumAbsenteeReporting": "1", "NumAbsenteeExpected": "1", "VoterCountQualified": "8615", "VoterCountVoted": "5143", "Choice": [{"ID": "3", "VoteTotal": "3194", "Outcome": null}, {"ID": "4", "VoteTotal": "1500", "Outcome": "Defeated"}]}, {"ID": "9708", "PrecinctsReporting": "24", "PrecinctsExpected": "24", "NumAbsenteeReporting": "1", "NumAbsenteeExpected": "1", "VoterCountQualified": "8615", "VoterCountVoted": "5143", "Choice": [{"ID": "3", "VoteTotal": "1029", "Outcome": null}, {"ID": "4", "VoteTotal": "3641", "Outcome": "Defeated"}]}, {"ID": "9709", "PrecinctsReporting": "24", "PrecinctsExpected": "24", "NumAbsenteeReporting": "1", "NumAbsenteeExpected": "1", "VoterCountQualified": "8615", "VoterCountVoted": "5143", "Choice": [{"ID": "3", "VoteTotal": "1046", "Outcome": null}, {"ID": "4", "VoteTotal": "3626", "Outcome": "Defeated"}]}]}}