{"Races": {"VersionDateTime": "1900-01-01T00:00:00", "Race": [{"ID": "51750", "PrecinctsReporting": "44", "PrecinctsExpected": "44", "NumAbsenteeReporting": "1", "NumAbsenteeExpected": "1", "VoterCountQualified": "14329", "VoterCountVoted": "3360", "Choice": [{"ID": "100157", "VoteTotal": "63", "Outcome": "Defeated"}, {"ID": "99011", "VoteTotal": "2245", "Outcome": "Elected"}, {"ID": "99808", "VoteTotal": "16", "Outcome": "Defeated"}, {"ID": "99156", "VoteTotal": "11", "Outcome": "Defeated"}, {"ID": "99760", "VoteTotal": "16", "Outcome": "Defeated"}, {"ID": "99339", "VoteTotal": "22", "Outcome": "Defeated"}, {"ID": "99317", "VoteTotal": "787", "Outcome": "Defeated"}, {"ID": "100546", "VoteTotal": "12", "Outcome": "Defeated"}, {"ID": "99436", "VoteTotal": "21", "Outcome": "Defeated"}, {"ID": "99729", "VoteTotal": "53", "Outcome": "Defeated"}]}, {"ID": "52072", "PrecinctsReporting": "36", "PrecinctsExpected": "36", "NumAbsenteeReporting": "1", "NumAbsenteeExpected": "1", "VoterCountQualified": "10535", "VoterCountVoted": "2387", "Choice": [{"ID": "100781", "VoteTotal": "762", "Outcome": "Defeated"}, {"ID": "100701", "VoteTotal": "981", "Outcome": "Elected"}]}, {"ID": "51751", "PrecinctsReporting": "44", "PrecinctsExpected": "44", "NumAbsenteeReporting": "1", "NumAbsenteeExpected": "1", "VoterCountQualified": "11012", "VoterCountVoted": "3890", "Choice": [{"ID": "99554", "VoteTotal": "20", "Outcome": "Defeated"}, {"ID": "99330", "VoteTotal": "45", "Outcome": "Defeated"}, {"ID": "99309", "VoteTotal": "3", "Outcome": "Defeated"}, {"ID": "100146", "VoteTotal": "1", "Outcome": "Defeated"}, {"ID": "99658", "VoteTotal": "1355", "Outcome": "Defeated"}, {"ID": "99078", "VoteTotal": "2", "Outcome": "Defeated"}, {"ID": "99501", "VoteTotal": "1", "Outcome": "Defeated"}, {"ID": "99005", "VoteTotal": "6", "Outcome": "Defeated"}, {"ID": "99368", "VoteTotal": "245", "Outcome": "Defeated"}, {"ID": "99629", "VoteTotal": "0", "Outcome": "Defeated"}, {"ID": "99722", "VoteTotal": "12", "Outcome": "Defeated"}, {"ID": "99798", "VoteTotal": "423", "Outcome": "Defeated"}, {"ID": "99354", "VoteTotal": "3", "Outcome": "Defeated"}, {"ID": "99060", "VoteTotal": "1846", "Outcome": "Elected"}]}, {"ID": "53732", "PrecinctsReporting": "14", "PrecinctsExpected": "14", "NumAbsenteeReporting": "1", "NumAbsenteeExpected": "1", "VoterCountQualified": "3712", "VoterCountVoted": "1294", "Choice": [{"ID": "99355", "VoteTotal": "220", "Outcome": "Defeated"}, {"ID": "100345", "VoteTotal": "480", "Outcome": "Elected"}]}]}}